pplay/__init__.py
pplay/animation.py
pplay/baseobject.py
pplay/collision.py
pplay/constants.py
pplay/exceptions.py
pplay/gameimage.py
pplay/gameobject.py
pplay/keyboard.py
pplay/mouse.py
pplay/point.py
pplay/sound.py
pplay/sprite.py
pplay/text.py
pplay/window.py
pplay_pygame-2.2.0.dist-info/LICENSE.rst
pplay_pygame-2.2.0.dist-info/METADATA
pplay_pygame-2.2.0.dist-info/WHEEL
pplay_pygame-2.2.0.dist-info/top_level.txt
pplay_pygame-2.2.0.dist-info/RECORD
